{
  "b": 209,
  "disableInputWhenNotFocused": true,
  "mangledName": "Menu_95",
  "name": "Menu_",
  "r": 209,
  "standardSortMethod": true,
  "stopSoundsOnStartup": true,
  "title": "",
  "v": 209,
  "uiSettings": {
    "grid": false,
    "gridType": "rectangular",
    "gridWidth": 32,
    "gridHeight": 32,
    "gridOffsetX": 0,
    "gridOffsetY": 0,
    "gridColor": 10401023,
    "gridAlpha": 0.8,
    "snap": false,
    "zoomFactor": 0.4659614187057792,
    "windowMask": false,
    "selectedLayer": "BOTONES"
  },
  "objectsGroups": [],
  "variables": [],
  "instances": [
    {
      "angle": 0,
      "customSize": true,
      "depth": 1,
      "height": 749,
      "keepRatio": true,
      "layer": "",
      "name": "BgMenu",
      "persistentUuid": "3095c5c6-14af-4e00-939d-7d42bc6d1086",
      "width": 848,
      "x": -11,
      "y": -53,
      "zOrder": -2,
      "numberProperties": [],
      "stringProperties": [],
      "initialVariables": []
    },
    {
      "angle": 0,
      "customSize": true,
      "depth": 1,
      "height": 67,
      "keepRatio": true,
      "layer": "BOTONES",
      "name": "titulo",
      "persistentUuid": "41b21682-adb6-4579-8592-4e45d49bbdc5",
      "width": 587,
      "x": 16,
      "y": 28,
      "zOrder": 1,
      "numberProperties": [],
      "stringProperties": [],
      "initialVariables": []
    },
    {
      "angle": 0,
      "customSize": true,
      "depth": 1,
      "height": 270,
      "keepRatio": true,
      "layer": "BOTONES",
      "name": "salem",
      "persistentUuid": "10804e89-0c01-4915-bc8b-ce4e6c141859",
      "width": 197,
      "x": 27,
      "y": 320,
      "zOrder": 2,
      "numberProperties": [],
      "stringProperties": [],
      "initialVariables": []
    },
    {
      "angle": 0,
      "customSize": true,
      "depth": 1,
      "height": 39,
      "keepRatio": true,
      "layer": "",
      "name": "item1",
      "persistentUuid": "052ceed4-c351-4c41-b30d-e0e5f5d9269b",
      "width": 104,
      "x": 285,
      "y": 143,
      "zOrder": 4,
      "numberProperties": [],
      "stringProperties": [],
      "initialVariables": []
    },
    {
      "angle": 0,
      "customSize": false,
      "height": 0,
      "keepRatio": true,
      "layer": "",
      "name": "slot1",
      "persistentUuid": "bbccc16e-2c66-4c32-bbde-26862acb6e6b",
      "width": 0,
      "x": 192,
      "y": 128,
      "zOrder": 8,
      "numberProperties": [],
      "stringProperties": [],
      "initialVariables": []
    },
    {
      "angle": 0,
      "customSize": false,
      "height": 0,
      "keepRatio": true,
      "layer": "",
      "name": "slot2",
      "persistentUuid": "dca04558-5444-4f18-b2f7-c0b7bc322ed0",
      "width": 0,
      "x": 192,
      "y": 192,
      "zOrder": 9,
      "numberProperties": [],
      "stringProperties": [],
      "initialVariables": []
    },
    {
      "angle": 0,
      "customSize": false,
      "height": 0,
      "keepRatio": true,
      "layer": "",
      "name": "slot3",
      "persistentUuid": "51d5d7ba-e657-4771-926f-5b19ff5dc6a4",
      "width": 0,
      "x": 192,
      "y": 256,
      "zOrder": 10,
      "numberProperties": [],
      "stringProperties": [],
      "initialVariables": []
    },
    {
      "angle": 0,
      "customSize": false,
      "height": 0,
      "keepRatio": true,
      "layer": "",
      "name": "slot4",
      "persistentUuid": "106b304a-e2b4-4510-a06b-0a52f71e0f6f",
      "width": 0,
      "x": 192,
      "y": 320,
      "zOrder": 11,
      "numberProperties": [],
      "stringProperties": [],
      "initialVariables": []
    },
    {
      "angle": 0,
      "customSize": true,
      "depth": 1,
      "height": 64,
      "keepRatio": true,
      "layer": "",
      "name": "cursor",
      "persistentUuid": "9a656b2f-656a-450d-8498-f5ccbc72c5d4",
      "width": 288,
      "x": 192,
      "y": 128,
      "zOrder": -1,
      "numberProperties": [],
      "stringProperties": [],
      "initialVariables": []
    },
    {
      "angle": 0,
      "customSize": false,
      "height": 0,
      "keepRatio": true,
      "layer": "",
      "name": "como_jugar",
      "persistentUuid": "a87f0483-5830-4182-a391-6fe99bccd804",
      "width": 0,
      "x": 246,
      "y": 209,
      "zOrder": 12,
      "numberProperties": [],
      "stringProperties": [],
      "initialVariables": []
    },
    {
      "angle": 0,
      "customSize": false,
      "height": 0,
      "keepRatio": true,
      "layer": "",
      "name": "HISTORIA",
      "persistentUuid": "351b29e9-e906-4cce-9b21-b796f4257d77",
      "width": 0,
      "x": 273,
      "y": 271,
      "zOrder": 13,
      "numberProperties": [],
      "stringProperties": [],
      "initialVariables": []
    },
    {
      "angle": 0,
      "customSize": false,
      "height": 0,
      "keepRatio": true,
      "layer": "",
      "name": "CONFIGURACION",
      "persistentUuid": "7c4b9634-822d-4fb7-a1b6-79b39b68664d",
      "width": 0,
      "x": 234,
      "y": 340,
      "zOrder": 14,
      "numberProperties": [],
      "stringProperties": [],
      "initialVariables": []
    },
    {
      "angle": 0,
      "customSize": false,
      "height": 0,
      "keepRatio": true,
      "layer": "",
      "name": "CREDITOS",
      "persistentUuid": "26a2c655-4a5e-4b64-b3f6-b6c23ddfeaba",
      "width": 0,
      "x": 274,
      "y": 405,
      "zOrder": 15,
      "numberProperties": [],
      "stringProperties": [],
      "initialVariables": []
    },
    {
      "angle": 0,
      "customSize": false,
      "height": 0,
      "keepRatio": true,
      "layer": "",
      "name": "slot5",
      "persistentUuid": "73d629c0-67c9-47a1-b539-1419ef35f286",
      "width": 0,
      "x": 192,
      "y": 384,
      "zOrder": 16,
      "numberProperties": [],
      "stringProperties": [],
      "initialVariables": []
    },
    {
      "angle": 0,
      "customSize": false,
      "height": 0,
      "keepRatio": true,
      "layer": "",
      "name": "piedra_der",
      "persistentUuid": "e70fcde1-cb04-4548-8776-f5f6ff18607d",
      "width": 0,
      "x": 511,
      "y": 431,
      "zOrder": 17,
      "numberProperties": [],
      "stringProperties": [],
      "initialVariables": []
    },
    {
      "angle": 0,
      "customSize": false,
      "height": 0,
      "keepRatio": true,
      "layer": "",
      "name": "piedra_izq",
      "persistentUuid": "a48b7b55-09aa-4a1d-9922-9c35f236bfcf",
      "width": 0,
      "x": -10,
      "y": 491,
      "zOrder": 18,
      "numberProperties": [],
      "stringProperties": [],
      "initialVariables": []
    }
  ],
  "objects": [
    {
      "adaptCollisionMaskAutomatically": true,
      "assetStoreId": "",
      "name": "BgMenu",
      "type": "Sprite",
      "updateIfNotVisible": false,
      "variables": [],
      "effects": [],
      "behaviors": [],
      "animations": [
        {
          "name": "",
          "useMultipleDirections": false,
          "directions": [
            {
              "looping": false,
              "timeBetweenFrames": 0.08,
              "sprites": [
                {
                  "hasCustomCollisionMask": true,
                  "image": "bg2.png",
                  "points": [],
                  "originPoint": {
                    "name": "origine",
                    "x": 0,
                    "y": 0
                  },
                  "centerPoint": {
                    "automatic": true,
                    "name": "centre",
                    "x": 0,
                    "y": 0
                  },
                  "customCollisionMask": [
                    [
                      {
                        "x": 0,
                        "y": 0
                      },
                      {
                        "x": 1024,
                        "y": 0
                      },
                      {
                        "x": 1024,
                        "y": 1024
                      },
                      {
                        "x": 0,
                        "y": 1024
                      }
                    ]
                  ]
                }
              ]
            }
          ]
        }
      ]
    },
    {
      "assetStoreId": "",
      "bold": false,
      "italic": false,
      "name": "titulo",
      "smoothed": true,
      "type": "TextObject::Text",
      "underlined": false,
      "variables": [],
      "effects": [],
      "behaviors": [],
      "string": "SALEM, EL REGRESO",
      "font": "BoldPixels.otf",
      "textAlignment": "left",
      "characterSize": 64,
      "color": {
        "b": 248,
        "g": 248,
        "r": 248
      },
      "content": {
        "bold": false,
        "isOutlineEnabled": false,
        "isShadowEnabled": true,
        "italic": false,
        "outlineColor": "255;255;255",
        "outlineThickness": 2,
        "shadowAngle": 90,
        "shadowBlurRadius": 2,
        "shadowColor": "0;0;0",
        "shadowDistance": 4,
        "shadowOpacity": 127,
        "smoothed": true,
        "underlined": false,
        "text": "SALEM, EL REGRESO",
        "font": "BoldPixels.otf",
        "textAlignment": "left",
        "verticalTextAlignment": "top",
        "characterSize": 64,
        "lineHeight": 0,
        "color": "248;248;248"
      }
    },
    {
      "adaptCollisionMaskAutomatically": true,
      "assetStoreId": "",
      "name": "salem",
      "type": "Sprite",
      "updateIfNotVisible": false,
      "variables": [],
      "effects": [],
      "behaviors": [],
      "animations": [
        {
          "name": "",
          "useMultipleDirections": false,
          "directions": [
            {
              "looping": false,
              "timeBetweenFrames": 0.08,
              "sprites": [
                {
                  "hasCustomCollisionMask": true,
                  "image": "salembgremove.png",
                  "points": [],
                  "originPoint": {
                    "name": "origine",
                    "x": 0,
                    "y": 0
                  },
                  "centerPoint": {
                    "automatic": true,
                    "name": "centre",
                    "x": 0,
                    "y": 0
                  },
                  "customCollisionMask": [
                    [
                      {
                        "x": 30,
                        "y": 97
                      },
                      {
                        "x": 394,
                        "y": 97
                      },
                      {
                        "x": 394,
                        "y": 541
                      },
                      {
                        "x": 30,
                        "y": 541
                      }
                    ]
                  ]
                }
              ]
            }
          ]
        }
      ]
    },
    {
      "assetStoreId": "",
      "bold": true,
      "italic": false,
      "name": "item1",
      "smoothed": true,
      "type": "TextObject::Text",
      "underlined": false,
      "variables": [],
      "effects": [],
      "behaviors": [],
      "string": "JUGAR",
      "font": "BoldPixels.otf",
      "textAlignment": "left",
      "characterSize": 36,
      "color": {
        "b": 20,
        "g": 2,
        "r": 158
      },
      "content": {
        "bold": true,
        "isOutlineEnabled": true,
        "isShadowEnabled": false,
        "italic": false,
        "outlineColor": "209;209;209",
        "outlineThickness": 2,
        "shadowAngle": 90,
        "shadowBlurRadius": 2,
        "shadowColor": "117;116;116",
        "shadowDistance": 4,
        "shadowOpacity": 127,
        "smoothed": true,
        "underlined": false,
        "text": "JUGAR",
        "font": "BoldPixels.otf",
        "textAlignment": "left",
        "verticalTextAlignment": "top",
        "characterSize": 36,
        "lineHeight": 0,
        "color": "158;2;20"
      }
    },
    {
      "adaptCollisionMaskAutomatically": true,
      "assetStoreId": "",
      "name": "slot1",
      "type": "Sprite",
      "updateIfNotVisible": false,
      "variables": [],
      "effects": [],
      "behaviors": [],
      "animations": [
        {
          "name": "NewSprite",
          "useMultipleDirections": false,
          "directions": [
            {
              "looping": false,
              "metadata": "{\"pskl\":{}}",
              "timeBetweenFrames": 0.08,
              "sprites": [
                {
                  "hasCustomCollisionMask": true,
                  "image": "NewSprite2",
                  "points": [],
                  "originPoint": {
                    "name": "origine",
                    "x": 0,
                    "y": 0
                  },
                  "centerPoint": {
                    "automatic": true,
                    "name": "centre",
                    "x": 0,
                    "y": 0
                  },
                  "customCollisionMask": [
                    [
                      {
                        "x": 0,
                        "y": 0
                      },
                      {
                        "x": 64,
                        "y": 0
                      },
                      {
                        "x": 64,
                        "y": 64
                      },
                      {
                        "x": 0,
                        "y": 64
                      }
                    ]
                  ]
                }
              ]
            }
          ]
        }
      ]
    },
    {
      "adaptCollisionMaskAutomatically": true,
      "assetStoreId": "",
      "name": "slot2",
      "type": "Sprite",
      "updateIfNotVisible": false,
      "variables": [],
      "effects": [],
      "behaviors": [],
      "animations": [
        {
          "name": "NewSprite",
          "useMultipleDirections": false,
          "directions": [
            {
              "looping": false,
              "metadata": "{\"pskl\":{}}",
              "timeBetweenFrames": 0.08,
              "sprites": [
                {
                  "hasCustomCollisionMask": true,
                  "image": "NewSprite2",
                  "points": [],
                  "originPoint": {
                    "name": "origine",
                    "x": 0,
                    "y": 0
                  },
                  "centerPoint": {
                    "automatic": true,
                    "name": "centre",
                    "x": 0,
                    "y": 0
                  },
                  "customCollisionMask": [
                    [
                      {
                        "x": 0,
                        "y": 0
                      },
                      {
                        "x": 64,
                        "y": 0
                      },
                      {
                        "x": 64,
                        "y": 64
                      },
                      {
                        "x": 0,
                        "y": 64
                      }
                    ]
                  ]
                }
              ]
            }
          ]
        }
      ]
    },
    {
      "adaptCollisionMaskAutomatically": true,
      "assetStoreId": "",
      "name": "slot3",
      "type": "Sprite",
      "updateIfNotVisible": false,
      "variables": [],
      "effects": [],
      "behaviors": [],
      "animations": [
        {
          "name": "NewSprite",
          "useMultipleDirections": false,
          "directions": [
            {
              "looping": false,
              "metadata": "{\"pskl\":{}}",
              "timeBetweenFrames": 0.08,
              "sprites": [
                {
                  "hasCustomCollisionMask": true,
                  "image": "NewSprite2",
                  "points": [],
                  "originPoint": {
                    "name": "origine",
                    "x": 0,
                    "y": 0
                  },
                  "centerPoint": {
                    "automatic": true,
                    "name": "centre",
                    "x": 0,
                    "y": 0
                  },
                  "customCollisionMask": [
                    [
                      {
                        "x": 0,
                        "y": 0
                      },
                      {
                        "x": 64,
                        "y": 0
                      },
                      {
                        "x": 64,
                        "y": 64
                      },
                      {
                        "x": 0,
                        "y": 64
                      }
                    ]
                  ]
                }
              ]
            }
          ]
        }
      ]
    },
    {
      "adaptCollisionMaskAutomatically": true,
      "assetStoreId": "",
      "name": "slot4",
      "type": "Sprite",
      "updateIfNotVisible": false,
      "variables": [],
      "effects": [],
      "behaviors": [],
      "animations": [
        {
          "name": "NewSprite",
          "useMultipleDirections": false,
          "directions": [
            {
              "looping": false,
              "metadata": "{\"pskl\":{}}",
              "timeBetweenFrames": 0.08,
              "sprites": [
                {
                  "hasCustomCollisionMask": true,
                  "image": "NewSprite2",
                  "points": [],
                  "originPoint": {
                    "name": "origine",
                    "x": 0,
                    "y": 0
                  },
                  "centerPoint": {
                    "automatic": true,
                    "name": "centre",
                    "x": 0,
                    "y": 0
                  },
                  "customCollisionMask": [
                    [
                      {
                        "x": 0,
                        "y": 0
                      },
                      {
                        "x": 64,
                        "y": 0
                      },
                      {
                        "x": 64,
                        "y": 64
                      },
                      {
                        "x": 0,
                        "y": 64
                      }
                    ]
                  ]
                }
              ]
            }
          ]
        }
      ]
    },
    {
      "adaptCollisionMaskAutomatically": true,
      "assetStoreId": "",
      "name": "cursor",
      "type": "Sprite",
      "updateIfNotVisible": false,
      "variables": [],
      "effects": [],
      "behaviors": [],
      "animations": [
        {
          "name": "NewSprite",
          "useMultipleDirections": false,
          "directions": [
            {
              "looping": false,
              "metadata": "{\"pskl\":{}}",
              "timeBetweenFrames": 0.08,
              "sprites": [
                {
                  "hasCustomCollisionMask": true,
                  "image": "NewSprite6",
                  "points": [],
                  "originPoint": {
                    "name": "origine",
                    "x": 0,
                    "y": 0
                  },
                  "centerPoint": {
                    "automatic": true,
                    "name": "centre",
                    "x": 0,
                    "y": 0
                  },
                  "customCollisionMask": [
                    [
                      {
                        "x": 11,
                        "y": 5
                      },
                      {
                        "x": 245,
                        "y": 5
                      },
                      {
                        "x": 245,
                        "y": 78
                      },
                      {
                        "x": 11,
                        "y": 78
                      }
                    ]
                  ]
                }
              ]
            }
          ]
        }
      ]
    },
    {
      "assetStoreId": "",
      "bold": true,
      "italic": false,
      "name": "como_jugar",
      "smoothed": true,
      "type": "TextObject::Text",
      "underlined": false,
      "variables": [],
      "effects": [],
      "behaviors": [],
      "string": "¿COMO JUGAR?",
      "font": "BoldPixels.otf",
      "textAlignment": "left",
      "characterSize": 28,
      "color": {
        "b": 20,
        "g": 2,
        "r": 158
      },
      "content": {
        "bold": true,
        "isOutlineEnabled": true,
        "isShadowEnabled": false,
        "italic": false,
        "outlineColor": "209;209;209",
        "outlineThickness": 2,
        "shadowAngle": 90,
        "shadowBlurRadius": 2,
        "shadowColor": "117;116;116",
        "shadowDistance": 4,
        "shadowOpacity": 127,
        "smoothed": true,
        "underlined": false,
        "text": "¿COMO JUGAR?",
        "font": "BoldPixels.otf",
        "textAlignment": "left",
        "verticalTextAlignment": "top",
        "characterSize": 28,
        "lineHeight": 0,
        "color": "158;2;20"
      }
    },
    {
      "assetStoreId": "",
      "bold": true,
      "italic": false,
      "name": "HISTORIA",
      "smoothed": true,
      "type": "TextObject::Text",
      "underlined": false,
      "variables": [],
      "effects": [],
      "behaviors": [],
      "string": "HISTORIA",
      "font": "BoldPixels.otf",
      "textAlignment": "left",
      "characterSize": 28,
      "color": {
        "b": 20,
        "g": 2,
        "r": 158
      },
      "content": {
        "bold": true,
        "isOutlineEnabled": true,
        "isShadowEnabled": false,
        "italic": false,
        "outlineColor": "209;209;209",
        "outlineThickness": 2,
        "shadowAngle": 90,
        "shadowBlurRadius": 2,
        "shadowColor": "117;116;116",
        "shadowDistance": 4,
        "shadowOpacity": 127,
        "smoothed": true,
        "underlined": false,
        "text": "HISTORIA",
        "font": "BoldPixels.otf",
        "textAlignment": "left",
        "verticalTextAlignment": "top",
        "characterSize": 28,
        "lineHeight": 0,
        "color": "158;2;20"
      }
    },
    {
      "assetStoreId": "",
      "bold": true,
      "italic": false,
      "name": "CREDITOS",
      "smoothed": true,
      "type": "TextObject::Text",
      "underlined": false,
      "variables": [],
      "effects": [],
      "behaviors": [],
      "string": "CREDITOS",
      "font": "BoldPixels.otf",
      "textAlignment": "left",
      "characterSize": 28,
      "color": {
        "b": 20,
        "g": 2,
        "r": 158
      },
      "content": {
        "bold": true,
        "isOutlineEnabled": true,
        "isShadowEnabled": false,
        "italic": false,
        "outlineColor": "209;209;209",
        "outlineThickness": 2,
        "shadowAngle": 90,
        "shadowBlurRadius": 2,
        "shadowColor": "117;116;116",
        "shadowDistance": 4,
        "shadowOpacity": 127,
        "smoothed": true,
        "underlined": false,
        "text": "CREDITOS",
        "font": "BoldPixels.otf",
        "textAlignment": "left",
        "verticalTextAlignment": "top",
        "characterSize": 28,
        "lineHeight": 0,
        "color": "158;2;20"
      }
    },
    {
      "assetStoreId": "",
      "bold": true,
      "italic": false,
      "name": "CONFIGURACION",
      "smoothed": true,
      "type": "TextObject::Text",
      "underlined": false,
      "variables": [],
      "effects": [],
      "behaviors": [],
      "string": "CONFIGURACIÓN",
      "font": "BoldPixels.otf",
      "textAlignment": "left",
      "characterSize": 28,
      "color": {
        "b": 20,
        "g": 2,
        "r": 158
      },
      "content": {
        "bold": true,
        "isOutlineEnabled": true,
        "isShadowEnabled": false,
        "italic": false,
        "outlineColor": "209;209;209",
        "outlineThickness": 2,
        "shadowAngle": 90,
        "shadowBlurRadius": 2,
        "shadowColor": "117;116;116",
        "shadowDistance": 4,
        "shadowOpacity": 127,
        "smoothed": true,
        "underlined": false,
        "text": "CONFIGURACIÓN",
        "font": "BoldPixels.otf",
        "textAlignment": "left",
        "verticalTextAlignment": "top",
        "characterSize": 28,
        "lineHeight": 0,
        "color": "158;2;20"
      }
    },
    {
      "adaptCollisionMaskAutomatically": true,
      "assetStoreId": "",
      "name": "slot5",
      "type": "Sprite",
      "updateIfNotVisible": false,
      "variables": [],
      "effects": [],
      "behaviors": [],
      "animations": [
        {
          "name": "NewSprite",
          "useMultipleDirections": false,
          "directions": [
            {
              "looping": false,
              "metadata": "{\"pskl\":{}}",
              "timeBetweenFrames": 0.08,
              "sprites": [
                {
                  "hasCustomCollisionMask": true,
                  "image": "NewSprite2",
                  "points": [],
                  "originPoint": {
                    "name": "origine",
                    "x": 0,
                    "y": 0
                  },
                  "centerPoint": {
                    "automatic": true,
                    "name": "centre",
                    "x": 0,
                    "y": 0
                  },
                  "customCollisionMask": [
                    [
                      {
                        "x": 0,
                        "y": 0
                      },
                      {
                        "x": 64,
                        "y": 0
                      },
                      {
                        "x": 64,
                        "y": 64
                      },
                      {
                        "x": 0,
                        "y": 64
                      }
                    ]
                  ]
                }
              ]
            }
          ]
        }
      ]
    },
    {
      "adaptCollisionMaskAutomatically": true,
      "assetStoreId": "",
      "name": "piedra_der",
      "type": "Sprite",
      "updateIfNotVisible": false,
      "variables": [],
      "effects": [],
      "behaviors": [],
      "animations": [
        {
          "name": "",
          "useMultipleDirections": false,
          "directions": [
            {
              "looping": false,
              "timeBetweenFrames": 0.08,
              "sprites": [
                {
                  "hasCustomCollisionMask": true,
                  "image": "Untitled-30.png",
                  "points": [],
                  "originPoint": {
                    "name": "origine",
                    "x": 0,
                    "y": 0
                  },
                  "centerPoint": {
                    "automatic": true,
                    "name": "centre",
                    "x": 0,
                    "y": 0
                  },
                  "customCollisionMask": [
                    [
                      {
                        "x": 0,
                        "y": 3
                      },
                      {
                        "x": 366,
                        "y": 3
                      },
                      {
                        "x": 366,
                        "y": 576
                      },
                      {
                        "x": 0,
                        "y": 576
                      }
                    ]
                  ]
                }
              ]
            }
          ]
        }
      ]
    },
    {
      "adaptCollisionMaskAutomatically": true,
      "assetStoreId": "",
      "name": "piedra_izq",
      "type": "Sprite",
      "updateIfNotVisible": false,
      "variables": [],
      "effects": [],
      "behaviors": [],
      "animations": [
        {
          "name": "",
          "useMultipleDirections": false,
          "directions": [
            {
              "looping": false,
              "timeBetweenFrames": 0.08,
              "sprites": [
                {
                  "hasCustomCollisionMask": true,
                  "image": "Untitled-40.png",
                  "points": [],
                  "originPoint": {
                    "name": "origine",
                    "x": 0,
                    "y": 0
                  },
                  "centerPoint": {
                    "automatic": true,
                    "name": "centre",
                    "x": 0,
                    "y": 0
                  },
                  "customCollisionMask": [
                    [
                      {
                        "x": 0,
                        "y": 0
                      },
                      {
                        "x": 272,
                        "y": 0
                      },
                      {
                        "x": 272,
                        "y": 594
                      },
                      {
                        "x": 0,
                        "y": 594
                      }
                    ]
                  ]
                }
              ]
            }
          ]
        }
      ]
    },
    {
      "adaptCollisionMaskAutomatically": true,
      "assetStoreId": "",
      "name": "cadro_negro",
      "type": "Sprite",
      "updateIfNotVisible": false,
      "variables": [],
      "effects": [],
      "behaviors": [],
      "animations": [
        {
          "name": "",
          "useMultipleDirections": false,
          "directions": [
            {
              "looping": false,
              "metadata": "{\"pskl\":{}}",
              "timeBetweenFrames": 0.08,
              "sprites": [
                {
                  "hasCustomCollisionMask": true,
                  "image": "NewSprite7",
                  "points": [],
                  "originPoint": {
                    "name": "origine",
                    "x": 0,
                    "y": 0
                  },
                  "centerPoint": {
                    "automatic": true,
                    "name": "centre",
                    "x": 0,
                    "y": 0
                  },
                  "customCollisionMask": [
                    [
                      {
                        "x": 0,
                        "y": 0
                      },
                      {
                        "x": 64,
                        "y": 0
                      },
                      {
                        "x": 64,
                        "y": 64
                      },
                      {
                        "x": 0,
                        "y": 64
                      }
                    ]
                  ]
                }
              ]
            }
          ]
        }
      ]
    }
  ],
  "objectsFolderStructure": {
    "folderName": "__ROOT",
    "children": [
      {
        "objectName": "BgMenu"
      },
      {
        "objectName": "titulo"
      },
      {
        "objectName": "salem"
      },
      {
        "objectName": "item1"
      },
      {
        "objectName": "como_jugar"
      },
      {
        "objectName": "HISTORIA"
      },
      {
        "objectName": "CONFIGURACION"
      },
      {
        "objectName": "CREDITOS"
      },
      {
        "objectName": "slot1"
      },
      {
        "objectName": "slot2"
      },
      {
        "objectName": "slot3"
      },
      {
        "objectName": "slot4"
      },
      {
        "objectName": "slot5"
      },
      {
        "objectName": "cursor"
      },
      {
        "objectName": "piedra_der"
      },
      {
        "objectName": "piedra_izq"
      },
      {
        "objectName": "cadro_negro"
      }
    ]
  },
  "events": [
    {
      "type": "BuiltinCommonInstructions::Standard",
      "conditions": [
        {
          "type": {
            "value": "DepartScene"
          },
          "parameters": [
            ""
          ]
        }
      ],
      "actions": [
        {
          "type": {
            "value": "Cache"
          },
          "parameters": [
            "slot1"
          ]
        },
        {
          "type": {
            "value": "Cache"
          },
          "parameters": [
            "slot2"
          ]
        },
        {
          "type": {
            "value": "Cache"
          },
          "parameters": [
            "slot3"
          ]
        },
        {
          "type": {
            "value": "Cache"
          },
          "parameters": [
            "slot4"
          ]
        },
        {
          "type": {
            "value": "Cache"
          },
          "parameters": [
            "slot5"
          ]
        },
        {
          "type": {
            "value": "OpacityCapability::OpacityBehavior::SetValue"
          },
          "parameters": [
            "cadro_negro",
            "Opacity",
            "=",
            "0"
          ]
        }
      ]
    },
    {
      "type": "BuiltinCommonInstructions::Standard",
      "conditions": [
        {
          "type": {
            "value": "KeyFromTextJustPressed"
          },
          "parameters": [
            "",
            "\"Down\""
          ]
        },
        {
          "type": {
            "value": "PosY"
          },
          "parameters": [
            "cursor",
            "<",
            "384"
          ]
        },
        {
          "type": {
            "value": "BuiltinCommonInstructions::Once"
          },
          "parameters": []
        }
      ],
      "actions": [
        {
          "type": {
            "value": "MettreXY"
          },
          "parameters": [
            "cursor",
            "=",
            "cursor.X()",
            "=",
            "cursor.Y()+64"
          ]
        }
      ]
    },
    {
      "type": "BuiltinCommonInstructions::Standard",
      "conditions": [
        {
          "type": {
            "value": "KeyFromTextJustPressed"
          },
          "parameters": [
            "",
            "\"Up\""
          ]
        },
        {
          "type": {
            "value": "PosY"
          },
          "parameters": [
            "cursor",
            ">=",
            "129"
          ]
        },
        {
          "type": {
            "value": "BuiltinCommonInstructions::Once"
          },
          "parameters": []
        }
      ],
      "actions": [
        {
          "type": {
            "value": "MettreXY"
          },
          "parameters": [
            "cursor",
            "=",
            "cursor.X()",
            "=",
            "cursor.Y()-64"
          ]
        }
      ]
    },
    {
      "type": "BuiltinCommonInstructions::Standard",
      "conditions": [
        {
          "type": {
            "value": "CollisionNP"
          },
          "parameters": [
            "cursor",
            "slot1",
            "",
            "",
            ""
          ]
        },
        {
          "type": {
            "value": "KeyFromTextJustPressed"
          },
          "parameters": [
            "",
            "\"Space\""
          ]
        },
        {
          "type": {
            "value": "PosY"
          },
          "parameters": [
            "piedra_der",
            "!=",
            "5"
          ]
        },
        {
          "type": {
            "value": "PosX"
          },
          "parameters": [
            "piedra_der",
            "!=",
            "434"
          ]
        },
        {
          "type": {
            "value": "BuiltinCommonInstructions::Once"
          },
          "parameters": []
        }
      ],
      "actions": [
        {
          "type": {
            "value": "AddForceVersPos"
          },
          "parameters": [
            "piedra_der",
            "piedra_der.X()",
            "5",
            "434",
            "1"
          ]
        }
      ]
    },
    {
      "type": "BuiltinCommonInstructions::Standard",
      "conditions": [],
      "actions": []
    }
  ],
  "layers": [
    {
      "ambientLightColorB": 200,
      "ambientLightColorG": 200,
      "ambientLightColorR": 200,
      "camera3DFarPlaneDistance": 10000,
      "camera3DFieldOfView": 45,
      "camera3DNearPlaneDistance": 3,
      "cameraType": "",
      "followBaseLayerCamera": false,
      "isLightingLayer": false,
      "isLocked": false,
      "name": "",
      "renderingType": "",
      "visibility": true,
      "cameras": [
        {
          "defaultSize": true,
          "defaultViewport": true,
          "height": 0,
          "viewportBottom": 1,
          "viewportLeft": 0,
          "viewportRight": 1,
          "viewportTop": 0,
          "width": 0
        }
      ],
      "effects": [
        {
          "effectType": "Scene3D::HemisphereLight",
          "name": "3D Ambient Hemisphere Light",
          "doubleParameters": {
            "elevation": 40,
            "intensity": 0.33,
            "rotation": 300
          },
          "stringParameters": {
            "groundColor": "127;127;127",
            "skyColor": "255;255;255",
            "top": "Z+"
          },
          "booleanParameters": {}
        },
        {
          "effectType": "Scene3D::DirectionalLight",
          "name": "3D Sun Light",
          "doubleParameters": {
            "distanceFromCamera": 1500,
            "elevation": 40,
            "frustumSize": 4000,
            "intensity": 0.75,
            "minimumShadowBias": 0,
            "rotation": 300
          },
          "stringParameters": {
            "color": "255;255;255",
            "shadowQuality": "medium",
            "top": "Z+"
          },
          "booleanParameters": {
            "isCastingShadow": true
          }
        }
      ]
    },
    {
      "ambientLightColorB": 200,
      "ambientLightColorG": 200,
      "ambientLightColorR": 200,
      "camera3DFarPlaneDistance": 10000,
      "camera3DFieldOfView": 45,
      "camera3DNearPlaneDistance": 3,
      "cameraType": "",
      "followBaseLayerCamera": false,
      "isLightingLayer": false,
      "isLocked": false,
      "name": "BOTONES",
      "renderingType": "",
      "visibility": true,
      "cameras": [],
      "effects": [
        {
          "effectType": "Scene3D::HemisphereLight",
          "name": "3D Ambient Hemisphere Light",
          "doubleParameters": {
            "elevation": 40,
            "intensity": 0.33,
            "rotation": 300
          },
          "stringParameters": {
            "groundColor": "127;127;127",
            "skyColor": "255;255;255",
            "top": "Z+"
          },
          "booleanParameters": {}
        },
        {
          "effectType": "Scene3D::DirectionalLight",
          "name": "3D Sun Light",
          "doubleParameters": {
            "distanceFromCamera": 1500,
            "elevation": 40,
            "frustumSize": 4000,
            "intensity": 0.75,
            "minimumShadowBias": 0,
            "rotation": 300
          },
          "stringParameters": {
            "color": "255;255;255",
            "shadowQuality": "medium",
            "top": "Z+"
          },
          "booleanParameters": {
            "isCastingShadow": true
          }
        }
      ]
    }
  ],
  "behaviorsSharedData": [
    {
      "name": "Animation",
      "type": "AnimatableCapability::AnimatableBehavior"
    },
    {
      "name": "Effect",
      "type": "EffectCapability::EffectBehavior"
    },
    {
      "name": "Flippable",
      "type": "FlippableCapability::FlippableBehavior"
    },
    {
      "name": "Opacity",
      "type": "OpacityCapability::OpacityBehavior"
    },
    {
      "name": "Resizable",
      "type": "ResizableCapability::ResizableBehavior"
    },
    {
      "name": "Scale",
      "type": "ScalableCapability::ScalableBehavior"
    },
    {
      "name": "Text",
      "type": "TextContainerCapability::TextContainerBehavior"
    }
  ]
}